http_inspector/__init__.py
http_inspector/__main__.py
http_inspector/handler.py
http_inspector/logger/__init__.py
http_inspector/logger/file_logger.py
http_inspector/logger/rich_logger.py
http_inspector/models.py
http_inspector/server.py
http_inspector/utils.py
hyper_inspector-0.0.5.dist-info/entry_points.txt
hyper_inspector-0.0.5.dist-info/WHEEL
hyper_inspector-0.0.5.dist-info/METADATA
hyper_inspector-0.0.5.dist-info/RECORD
